{
  "english": {
    "A1": [
      { "w": "apple", "p": "/藞忙p.蓹l/", "t": "褟斜谢褍泻芯" },
      { "w": "book", "p": "/b蕣k/", "t": "泻薪懈谐邪" }
    ],
    "A2": [
      { "w": "development", "p": "/d瑟藞vel.蓹p.m蓹nt/", "t": "褉芯蟹胁懈褌芯泻" }
    ],
    "B1": [
      { "w": "ability", "p": "/蓹藞b瑟l.蓹.ti/", "t": "蟹写邪褌薪褨褋褌褜 / 胁屑褨薪薪褟" },
      { "w": "absolute", "p": "/藞忙b.s蓹.lu藧t/", "t": "邪斜褋芯谢褞褌薪懈泄 / 褑褨谢泻芯胁懈褌懈泄" },
      { "w": "achieve", "p": "/蓹藞t蕛i藧v/", "t": "写芯褋褟谐邪褌懈 / 写芯斜懈胁邪褌懈褋褟" },
      { "w": "activity", "p": "/忙k藞t瑟v.蓹.ti/", "t": "写褨褟谢褜薪褨褋褌褜 / 邪泻褌懈胁薪褨褋褌褜" },
      { "w": "additional", "p": "/蓹藞d瑟蕛.蓹n.蓹l/", "t": "写芯写邪褌泻芯胁懈泄" },
      { "w": "advertise", "p": "/藞忙d.v蓹.ta瑟z/", "t": "褉械泻谢邪屑褍胁邪褌懈" },
      { "w": "afford", "p": "/蓹藞f蓴藧d/", "t": "写芯蟹胁芯谢懈褌懈 褋芯斜褨 (褎褨薪邪薪褋芯胁芯)" },
      { "w": "agreement", "p": "/蓹藞伞ri藧.m蓹nt/", "t": "褍谐芯写邪 / 蟹谐芯写邪" },
      { "w": "alternative", "p": "/蓲l藞t蓽藧.n蓹.t瑟v/", "t": "邪谢褜褌械褉薪邪褌懈胁邪 / 邪谢褜褌械褉薪邪褌懈胁薪懈泄" },
      { "w": "ambition", "p": "/忙m藞b瑟蕛.蓹n/", "t": "邪屑斜褨褑褨褟 / 锌褉邪谐薪械薪薪褟" },
      { "w": "amount", "p": "/蓹藞ma蕣nt/", "t": "泻褨谢褜泻褨褋褌褜 / 褋褍屑邪" },
      { "w": "ancient", "p": "/藞e瑟n.蕛蓹nt/", "t": "褋褌邪褉芯写邪胁薪褨泄 / 写褉械胁薪褨泄" },
      { "w": "anxious", "p": "/藞忙艐k.蕛蓹s/", "t": "褌褉懈胁芯卸薪懈泄 / 褋褌褍褉斜芯胁邪薪懈泄" },
      { "w": "appearance", "p": "/蓹藞p瑟蓹.r蓹ns/", "t": "蟹芯胁薪褨褕薪褨褋褌褜 / 锌芯褟胁邪" },
      { "w": "appointment", "p": "/蓹藞p蓴瑟nt.m蓹nt/", "t": "锌褉懈蟹薪邪褔械薪邪 蟹褍褋褌褉褨褔 (褍 褋锌褉邪胁褨)" },
      { "w": "appropriate", "p": "/蓹藞pr蓹蕣.pri.蓹t/", "t": "胁褨写锌芯胁褨写薪懈泄 / 写芯褉械褔薪懈泄" },
      { "w": "arrange", "p": "/蓹藞re瑟nd蕭/", "t": "芯褉谐邪薪褨蟹芯胁褍胁邪褌懈 / 胁谢邪褕褌芯胁褍胁邪褌懈" },
      { "w": "audience", "p": "/藞蓴藧.di.蓹ns/", "t": "邪褍写懈褌芯褉褨褟 / 锌褍斜谢褨泻邪" },
      { "w": "available", "p": "/蓹藞ve瑟.l蓹.b蓹l/", "t": "写芯褋褌褍锌薪懈泄 / 薪邪褟胁薪懈泄" },
      { "w": "average", "p": "/藞忙v.蓹r.瑟d蕭/", "t": "褋械褉械写薪褨泄 / 褋械褉械写薪褜芯褋褌邪褌懈褋褌懈褔薪懈泄" },
      { "w": "behavior", "p": "/b瑟藞he瑟.vj蓹r/", "t": "锌芯胁械写褨薪泻邪" },
      { "w": "benefit", "p": "/藞ben.瑟.f瑟t/", "t": "泻芯褉懈褋褌褜 / 胁懈谐芯写邪 / 锌械褉械胁邪谐邪" },
      { "w": "bother", "p": "/藞b蓲冒.蓹r/", "t": "褌褍褉斜褍胁邪褌懈 / 薪邪写芯泻褍褔邪褌懈" },
      { "w": "breathe", "p": "/bri藧冒/", "t": "写懈褏邪褌懈" },
      { "w": "cancel", "p": "/藞k忙n.s蓹l/", "t": "褋泻邪褋芯胁褍胁邪褌懈" },
      { "w": "candidate", "p": "/藞k忙n.d瑟.d蓹t/", "t": "泻邪薪写懈写邪褌" },
      { "w": "celebration", "p": "/藢sel.蓹藞bre瑟.蕛蓹n/", "t": "褋胁褟褌泻褍胁邪薪薪褟" },
      { "w": "century", "p": "/藞sen.t蕛蓹r.i/", "t": "褋褌芯谢褨褌褌褟" },
      { "w": "challenge", "p": "/藞t蕛忙l.瑟nd蕭/", "t": "胁懈泻谢懈泻 / 褋泻谢邪写薪械 蟹邪胁写邪薪薪褟" },
      { "w": "character", "p": "/藞k忙r.蓹k.t蓹r/", "t": "锌械褉褋芯薪邪卸 / 褏邪褉邪泻褌械褉 / 褔懈薪薪懈泻" },
      { "w": "charity", "p": "/藞t蕛忙r.蓹.ti/", "t": "斜谢邪谐芯写褨泄薪褨褋褌褜" },
      { "w": "citizen", "p": "/藞s瑟t.瑟.z蓹n/", "t": "谐褉芯屑邪写褟薪懈薪" },
      { "w": "combination", "p": "/藢k蓲m.b瑟藞ne瑟.蕛蓹n/", "t": "锌芯褦写薪邪薪薪褟 / 泻芯屑斜褨薪邪褑褨褟" },
      { "w": "comfort", "p": "/藞k蕦m.f蓹t/", "t": "泻芯屑褎芯褉褌 / 蟹邪褌懈褕芯泻" },
      { "w": "complain", "p": "/k蓹m藞ple瑟n/", "t": "褋泻邪褉卸懈褌懈褋褟" },
      { "w": "conclude", "p": "/k蓹n藞klu藧d/", "t": "褉芯斜懈褌懈 胁懈褋薪芯胁芯泻 / 蟹邪胁械褉褕褍胁邪褌懈" },
      { "w": "confident", "p": "/藞k蓲n.f瑟.d蓹nt/", "t": "胁锌械胁薪械薪懈泄 (褍 褋芯斜褨)" },
      { "w": "confirm", "p": "/k蓹n藞f蓽藧m/", "t": "锌褨写褌胁械褉写卸褍胁邪褌懈" },
      { "w": "confused", "p": "/k蓹n藞fju藧zd/", "t": "褉芯蟹谐褍斜谢械薪懈泄 / 蟹邪锌谢褍褌邪薪懈泄" },
      { "w": "consequence", "p": "/藞k蓲n.s瑟.kw蓹ns/", "t": "薪邪褋谢褨写芯泻" },
      { "w": "consumer", "p": "/k蓹n藞sju藧.m蓹r/", "t": "褋锌芯卸懈胁邪褔" },
      { "w": "continuous", "p": "/k蓹n藞t瑟n.ju.蓹s/", "t": "斜械蟹锌械褉械褉胁薪懈泄 / 褌褉懈胁邪谢懈泄" },
      { "w": "convince", "p": "/k蓹n藞v瑟ns/", "t": "锌械褉械泻芯薪褍胁邪褌懈" },
      { "w": "create", "p": "/kri藞e瑟t/", "t": "褋褌胁芯褉褞胁邪褌懈" },
      { "w": "crew", "p": "/kru藧/", "t": "械泻褨锌邪卸 / 泻芯屑邪薪写邪" },
      { "w": "cultural", "p": "/藞k蕦l.t蕛蓹r.蓹l/", "t": "泻褍谢褜褌褍褉薪懈泄" },
      { "w": "curious", "p": "/藞kj蕣蓹.ri.蓹s/", "t": "褑褨泻邪胁懈泄 / 写芯锌懈褌谢懈胁懈泄" },
      { "w": "current", "p": "/藞k蕦r.蓹nt/", "t": "锌芯褌芯褔薪懈泄 / 褋褍褔邪褋薪懈泄" },
      { "w": "damage", "p": "/藞d忙m.瑟d蕭/", "t": "褕泻芯写邪 / 蟹斜懈褌芯泻 / 锌芯褕泻芯写卸械薪薪褟" },
      { "w": "decision", "p": "/d瑟藞s瑟蕭.蓹n/", "t": "褉褨褕械薪薪褟" },
      { "w": "decrease", "p": "/d瑟藞kri藧s/", "t": "蟹屑械薪褕褍胁邪褌懈 / 蟹薪懈卸褍胁邪褌懈" },
      { "w": "deliver", "p": "/d瑟藞l瑟v.蓹r/", "t": "写芯褋褌邪胁谢褟褌懈" },
      { "w": "departure", "p": "/d瑟藞p蓱藧.t蕛蓹r/", "t": "胁褨写锌褉邪胁谢械薪薪褟 / 胁懈谢褨褌" },
      { "w": "description", "p": "/d瑟藞skr瑟p.蕛蓹n/", "t": "芯锌懈褋" },
      { "w": "deserve", "p": "/d瑟藞z蓽藧v/", "t": "蟹邪褋谢褍谐芯胁褍胁邪褌懈" },
      { "w": "development", "p": "/d瑟藞vel.蓹p.m蓹nt/", "t": "褉芯蟹胁懈褌芯泻 / 褉芯蟹褉芯斜泻邪" },
      { "w": "disappointed", "p": "/藢d瑟s.蓹藞p蓴瑟n.t瑟d/", "t": "褉芯蟹褔邪褉芯胁邪薪懈泄" },
      { "w": "discount", "p": "/藞d瑟s.ka蕣nt/", "t": "蟹薪懈卸泻邪" },
      { "w": "divide", "p": "/d瑟藞va瑟d/", "t": "写褨谢懈褌懈 / 褉芯蟹写褨谢褟褌懈" },
      { "w": "document", "p": "/藞d蓲k.j蓹.m蓹nt/", "t": "写芯泻褍屑械薪褌" },
      { "w": "dramatic", "p": "/dr蓹藞m忙t.瑟k/", "t": "写褉邪屑邪褌懈褔薪懈泄 / 褉褨蟹泻懈泄" },
      { "w": "education", "p": "/藢ed蕭.蕣藞ke瑟.蕛蓹n/", "t": "芯褋胁褨褌邪" },
      { "w": "efficient", "p": "/瑟藞f瑟蕛.蓹nt/", "t": "械褎械泻褌懈胁薪懈泄 / 锌褉芯写褍泻褌懈胁薪懈泄" },
      { "w": "embarrassed", "p": "/瑟m藞b忙r.蓹st/", "t": "蟹斜械薪褌械卸械薪懈泄 / 褋芯褉芯屑'褟蟹谢懈胁懈泄" },
      { "w": "emergency", "p": "/瑟藞m蓽藧.d蕭蓹n.si/", "t": "薪邪写蟹胁懈褔邪泄薪邪 褋懈褌褍邪褑褨褟" },
      { "w": "encourage", "p": "/瑟n藞k蕦r.瑟d蕭/", "t": "蟹邪芯褏芯褔褍胁邪褌懈 / 锌褨写斜邪写褜芯褉褞胁邪褌懈" },
      { "w": "environment", "p": "/瑟n藞va瑟.r蓹n.m蓹nt/", "t": "薪邪胁泻芯谢懈褕薪褦 褋械褉械写芯胁懈褖械" },
      { "w": "equipment", "p": "/瑟藞kw瑟p.m蓹nt/", "t": "芯斜谢邪写薪邪薪薪褟 / 褋锌芯褉褟写卸械薪薪褟" },
      { "w": "escape", "p": "/瑟藞ske瑟p/", "t": "胁褌械褔邪 / 胁褌褨泻邪褌懈" },
      { "w": "evidence", "p": "/藞ev.瑟.d蓹ns/", "t": "写芯泻邪蟹 / 褋胁褨写褔械薪薪褟" },
      { "w": "exhibition", "p": "/藢ek.s瑟藞b瑟蕛.蓹n/", "t": "胁懈褋褌邪胁泻邪" },
      { "w": "exist", "p": "/瑟伞藞z瑟st/", "t": "褨褋薪褍胁邪褌懈" },
      { "w": "expect", "p": "/瑟k藞spekt/", "t": "芯褔褨泻褍胁邪褌懈 / 褋锌芯写褨胁邪褌懈褋褟" },
      { "w": "experience", "p": "/瑟k藞sp瑟蓹.ri.蓹ns/", "t": "写芯褋胁褨写" },
      { "w": "exploration", "p": "/藢ek.spl蓹藞re瑟.蕛蓹n/", "t": "写芯褋谢褨写卸械薪薪褟 / 褉芯蟹胁褨写泻邪" },
      { "w": "expression", "p": "/瑟k藞spre蕛.蓹n/", "t": "胁懈褉邪蟹 / 胁懈褋谢褨胁" },
      { "w": "frequent", "p": "/藞fri藧.kw蓹nt/", "t": "褔邪褋褌懈泄" },
      { "w": "frightened", "p": "/藞fra瑟.t蓹nd/", "t": "薪邪谢褟泻邪薪懈泄" },
      { "w": "generate", "p": "/藞d蕭en.蓹.re瑟t/", "t": "谐械薪械褉褍胁邪褌懈 / 褋褌胁芯褉褞胁邪褌懈" },
      { "w": "government", "p": "/藞伞蕦v.蓹n.m蓹nt/", "t": "褍褉褟写" },
      { "w": "gradually", "p": "/藞伞r忙d蕭.u.蓹.li/", "t": "锌芯褋褌褍锌芯胁芯" },
      { "w": "guarantee", "p": "/藢伞忙r.蓹n藞ti藧/", "t": "谐邪褉邪薪褌褨褟 / 谐邪褉邪薪褌褍胁邪褌懈" },
      { "w": "guilty", "p": "/藞伞瑟l.ti/", "t": "胁懈薪薪懈泄" },
      { "w": "habit", "p": "/藞h忙b.瑟t/", "t": "蟹胁懈褔泻邪" },
      { "w": "hesitate", "p": "/藞hez.瑟.te瑟t/", "t": "胁邪谐邪褌懈褋褟" },
      { "w": "hire", "p": "/ha瑟蓹r/", "t": "薪邪泄屑邪褌懈 / 斜褉邪褌懈 胁 锌褉芯泻邪褌" },
      { "w": "identity", "p": "/a瑟藞den.t蓹.ti/", "t": "芯褋芯斜懈褋褌褨褋褌褜 / 褨写械薪褌懈褔薪褨褋褌褜" },
      { "w": "ignore", "p": "/瑟伞藞n蓴藧r/", "t": "褨谐薪芯褉褍胁邪褌懈" },
      { "w": "illegal", "p": "/瑟藞li藧.伞蓹l/", "t": "薪械蟹邪泻芯薪薪懈泄" },
      { "w": "imagine", "p": "/瑟藞m忙d蕭.瑟n/", "t": "褍褟胁谢褟褌懈" },
      { "w": "imitation", "p": "/藢瑟m.瑟藞te瑟.蕛蓹n/", "t": "褨屑褨褌邪褑褨褟 / 锌褨写褉芯斜泻邪" },
      { "w": "immediate", "p": "/瑟藞mi藧.di.蓹t/", "t": "薪械谐邪泄薪懈泄 / 褌械褉屑褨薪芯胁懈泄" },
      { "w": "importance", "p": "/瑟m藞p蓴藧.t蓹ns/", "t": "胁邪卸谢懈胁褨褋褌褜" },
      { "w": "improvement", "p": "/瑟m藞pru藧v.m蓹nt/", "t": "锌芯泻褉邪褖械薪薪褟" },
      { "w": "include", "p": "/瑟n藞klu藧d/", "t": "胁泻谢褞褔邪褌懈 胁 褋械斜械" },
      { "w": "independent", "p": "/藢瑟n.d瑟藞pen.d蓹nt/", "t": "薪械蟹邪谢械卸薪懈泄" },
      { "w": "industry", "p": "/藞瑟n.d蓹s.tri/", "t": "锌褉芯屑懈褋谢芯胁褨褋褌褜 / 褨薪写褍褋褌褉褨褟" },
      { "w": "infection", "p": "/瑟n藞fek.蕛蓹n/", "t": "褨薪褎械泻褑褨褟" },
      { "w": "influence", "p": "/藞瑟n.flu.蓹ns/", "t": "胁锌谢懈胁 / 胁锌谢懈胁邪褌懈" },
      { "w": "manage", "p": "/藞m忙n.瑟d蕭/", "t": "泻械褉褍胁邪褌懈 / 褋锌褉邪胁谢褟褌懈褋褟" }
    ],
    "B2": [],
    "C1": [
      { "w": "abandon", "p": "/蓹藞b忙n.d蓹n/", "t": "锌芯泻懈写邪褌懈 / 蟹邪谢懈褕邪褌懈 / 胁褨写屑芯胁谢褟褌懈褋褟" },
      { "w": "abstraction", "p": "/忙b藞str忙k.蕛蓹n/", "t": "邪斜褋褌褉邪泻褑褨褟 / 胁褨写胁芯谢褨泻邪薪薪褟" },
      { "w": "accumulate", "p": "/蓹藞kju藧.mj蓹.le瑟t/", "t": "薪邪泻芯锌懈褔褍胁邪褌懈 / 蟹斜懈褉邪褌懈" },
      { "w": "advocate", "p": "/藞忙d.v蓹.ke瑟t/", "t": "胁褨写褋褌芯褞胁邪褌懈 / 胁懈褋褌褍锌邪褌懈 薪邪 蟹邪褏懈褋褌" },
      { "w": "affluent", "p": "/藞忙f.lu.蓹nt/", "t": "斜邪谐邪褌懈泄 / 蟹邪斜械蟹锌械褔械薪懈泄 / 蟹邪屑芯卸薪懈泄" },
      { "w": "ambiguous", "p": "/忙m藞b瑟伞.ju.蓹s/", "t": "写胁芯蟹薪邪褔薪懈泄 / 薪械褟褋薪懈泄 / 薪械褔褨褌泻懈泄" },
      { "w": "anxious", "p": "/藞忙艐k.蕛蓹s/", "t": "褌褉懈胁芯卸薪懈泄 / 褋褌褍褉斜芯胁邪薪懈泄" },
      { "w": "appalling", "p": "/蓹藞p蓴藧.l瑟艐/", "t": "卸邪褏谢懈胁懈泄 / 锌褉懈谐芯谢芯屑褕谢懈胁懈泄" },
      { "w": "appropriate", "p": "/蓹藞pr蓹蕣.pri.蓹t/", "t": "胁褨写锌芯胁褨写薪懈泄 / 写芯褉械褔薪懈泄" },
      { "w": "arbitrary", "p": "/藞蓱藧.b瑟.tr蓹r.i/", "t": "写芯胁褨谢褜薪懈泄 / 胁懈锌邪写泻芯胁懈泄" },
      { "w": "assert", "p": "/蓹藞s蓽藧t/", "t": "褋褌胁械褉写卸褍胁邪褌懈 / 蟹邪褟胁谢褟褌懈 / 蟹邪褏懈褖邪褌懈 锌褉邪胁邪" },
      { "w": "attain", "p": "/蓹藞te瑟n/", "t": "写芯褋褟谐邪褌懈 / 蟹写芯斜褍胁邪褌懈" },
      { "w": "attribute", "p": "/蓹藞tr瑟b.ju藧t/", "t": "锌褉懈锌懈褋褍胁邪褌懈 (褔芯屑褍褋褜) / 锌芯胁'褟蟹褍胁邪褌懈 蟹" },
      { "w": "authentic", "p": "/蓴藧藞胃en.t瑟k/", "t": "邪胁褌械薪褌懈褔薪懈泄 / 褋锌褉邪胁卸薪褨泄" },
      { "w": "baffle", "p": "/藞b忙f.蓹l/", "t": "褋锌邪薪褌械谢懈褔褍胁邪褌懈 / 蟹斜懈胁邪褌懈 蟹 锌邪薪褌械谢懈泻褍" },
      { "w": "barren", "p": "/藞b忙r.蓹n/", "t": "斜械蟹锌谢褨写薪懈泄 / 锌褍褋褌懈泄 / 胁懈褋薪邪卸械薪懈泄" },
      { "w": "bias", "p": "/藞ba瑟.蓹s/", "t": "褍锌械褉械写卸械薪褨褋褌褜 / 褍褏懈谢 / 锌械褉械写胁蟹褟褌褨褋褌褜" },
      { "w": "bizarre", "p": "/b瑟藞z蓱藧r/", "t": "褏懈屑械褉薪懈泄 / 写懈胁薪懈泄 / 械泻褋褑械薪褌褉懈褔薪懈泄" },
      { "w": "blatant", "p": "/藞ble瑟.t蓹nt/", "t": "泻褉懈褔褍褖懈泄 / 褟胁薪懈泄 / 芯褔械胁懈写薪懈泄" },
      { "w": "breach", "p": "/bri藧t蕛/", "t": "锌芯褉褍褕械薪薪褟 (蟹邪泻芯薪褍, 泻芯薪褌褉邪泻褌褍) / 锌褉芯褉懈胁" },
      { "w": "candid", "p": "/藞k忙n.d瑟d/", "t": "胁褨写胁械褉褌懈泄 / 褖懈褉懈泄 / 锌褉褟屑懈泄" },
      { "w": "challenge", "p": "/藞t蕛忙l.瑟nd蕭/", "t": "胁懈泻谢懈泻 / 褋泻谢邪写薪械 蟹邪胁写邪薪薪褟" },
      { "w": "chronic", "p": "/藞kr蓲n.瑟k/", "t": "褏褉芯薪褨褔薪懈泄 / 锌芯褋褌褨泄薪懈泄" },
      { "w": "coherent", "p": "/k蓹蕣藞h瑟蓹.r蓹nt/", "t": "蟹胁'褟蟹薪懈泄 / 锌芯褋谢褨写芯胁薪懈泄 / 谢芯谐褨褔薪懈泄" },
      { "w": "coincide", "p": "/藢k蓹蕣.瑟n藞sa瑟d/", "t": "蟹斜褨谐邪褌懈褋褟 / 胁褨写斜褍胁邪褌懈褋褟 芯写薪芯褔邪褋薪芯" },
      { "w": "compelling", "p": "/k蓹m藞pel.瑟艐/", "t": "锌械褉械泻芯薪谢懈胁懈泄 / 薪械锌械褉械斜芯褉薪懈泄 / 蟹邪褏芯锌谢褞褞褔懈泄" },
      { "w": "compensate", "p": "/藞k蓲m.p蓹n.se瑟t/", "t": "泻芯屑锌械薪褋褍胁邪褌懈 / 胁褨写褕泻芯写芯胁褍胁邪褌懈" },
      { "w": "comply", "p": "/k蓹m藞pla瑟/", "t": "写芯褌褉懈屑褍胁邪褌懈褋褟 / 锌褨写泻芯褉褟褌懈褋褟 / 胁懈泻芯薪褍胁邪褌懈" },
      { "w": "concede", "p": "/k蓹n藞si藧d/", "t": "锌芯褋褌褍锌邪褌懈褋褟 / 胁懈蟹薪邪胁邪褌懈 (锌芯褉邪蟹泻褍, 锌褉邪胁芯褌褍)" },
      { "w": "concise", "p": "/k蓹n藞sa瑟s/", "t": "泻芯褉芯褌泻懈泄 / 褋褌懈褋谢懈泄" },
      { "w": "conducive", "p": "/k蓹n藞d蕭u藧.s瑟v/", "t": "褋锌褉懈褟褌谢懈胁懈泄 / 褟泻懈泄 褋锌褉懈褟褦" },
      { "w": "consequently", "p": "/藞k蓲n.s瑟.kw蓹nt.li/", "t": "褟泻 薪邪褋谢褨写芯泻 / 芯褌卸械 / 褌芯屑褍" },
      { "w": "contemplate", "p": "/藞k蓲n.t蓹m.ple瑟t/", "t": "屑褨褉泻褍胁邪褌懈 / 芯斜屑褨褉泻芯胁褍胁邪褌懈 / 褋锌芯谐谢褟写邪褌懈" },
      { "w": "contradict", "p": "/藢k蓲n.tr蓹藞d瑟kt/", "t": "褋褍锌械褉械褔懈褌懈 / 蟹邪锌械褉械褔褍胁邪褌懈" },
      { "w": "crucial", "p": "/藞kru藧.蕛蓹l/", "t": "胁懈褉褨褕邪谢褜薪懈泄 / 泻褉懈褌懈褔薪芯 胁邪卸谢懈胁懈泄" },
      { "w": "cynical", "p": "/藞s瑟n.瑟.k蓹l/", "t": "褑懈薪褨褔薪懈泄" },
      { "w": "deficiency", "p": "/d瑟藞f瑟蕛.蓹n.si/", "t": "写械褎褨褑懈褌 / 薪械褋褌邪褔邪 / 薪械写芯谢褨泻" },
      { "w": "deliberate", "p": "/d瑟藞l瑟b.蓹r.蓹t/", "t": "薪邪胁屑懈褋薪懈泄 / 褍屑懈褋薪懈泄 / 芯斜写褍屑邪薪懈泄" },
      { "w": "depict", "p": "/d瑟藞p瑟kt/", "t": "蟹芯斜褉邪卸邪褌懈 / 蟹屑邪谢褜芯胁褍胁邪褌懈" },
      { "w": "deteriorate", "p": "/d瑟藞t瑟蓹.ri.蓹.re瑟t/", "t": "锌芯谐褨褉褕褍胁邪褌懈褋褟 / 褋褌邪胁邪褌懈 谐褨褉褕懈屑" },
      { "w": "devastate", "p": "/藞dev.蓹.ste瑟t/", "t": "褋锌褍褋褌芯褕褍胁邪褌懈 / 褉芯蟹芯褉褟褌懈 / 锌褉懈谐薪褨褔褍胁邪褌懈" },
      { "w": "differentiate", "p": "/藢d瑟f.蓹藞ren.蕛i.e瑟t/", "t": "褉芯蟹褉褨蟹薪褟褌懈 / 褉芯蟹屑械卸芯胁褍胁邪褌懈" },
      { "w": "diligent", "p": "/藞d瑟l.瑟.d蕭蓹nt/", "t": "褋褌邪褉邪薪薪懈泄 / 锌褉邪褑褜芯胁懈褌懈泄" },
      { "w": "diminish", "p": "/d瑟藞m瑟n.瑟蕛/", "t": "蟹屑械薪褕褍胁邪褌懈 / 褋锌邪写邪褌懈" },
      { "w": "discard", "p": "/d瑟藞sk蓱藧d/", "t": "胁懈泻懈写邪褌懈 / 胁褨写泻懈写邪褌懈 蟹邪 薪械锌芯褌褉褨斜薪褨褋褌褞" },
      { "w": "discrepancy", "p": "/d瑟藞skrep.蓹n.si/", "t": "薪械胁褨写锌芯胁褨写薪褨褋褌褜 / 褉芯蟹斜褨卸薪褨褋褌褜" },
      { "w": "disrupt", "p": "/d瑟s藞r蕦pt/", "t": "锌褨写褉懈胁邪褌懈 / 锌芯褉褍褕褍胁邪褌懈 锌芯褉褟写芯泻" },
      { "w": "distort", "p": "/d瑟s藞t蓴藧t/", "t": "褋锌芯褌胁芯褉褞胁邪褌懈 / 锌械褉械泻褉褍褔褍胁邪褌懈 (褎邪泻褌懈)" },
      { "w": "diverse", "p": "/da瑟藞v蓽藧s/", "t": "褉褨蟹薪芯屑邪薪褨褌薪懈泄 / 褨薪褕懈泄" },
      { "w": "drastic", "p": "/藞dr忙s.t瑟k/", "t": "褉褨褕褍褔懈泄 / 褉邪写懈泻邪谢褜薪懈泄 / 褉褨蟹泻懈泄" },
      { "w": "dubious", "p": "/藞d蕭u藧.bi.蓹s/", "t": "褋褍屑薪褨胁薪懈泄 / 锌褨写芯蟹褉褨谢懈泄" },
      { "w": "durable", "p": "/藞d蕭蕣蓹.r蓹.b蓹l/", "t": "写芯胁谐芯胁褨褔薪懈泄 / 屑褨褑薪懈泄 / 褋褌褨泄泻懈泄" },
      { "w": "eccentric", "p": "/ek藞sen.tr瑟k/", "t": "械泻褋褑械薪褌褉懈褔薪懈泄 / 写懈胁邪泻褍胁邪褌懈泄" },
      { "w": "elaborate", "p": "/i藞l忙b.蓹r.蓹t/", "t": "褋泻谢邪写薪懈泄 / 写械褌邪谢褜薪芯 褉芯蟹褉芯斜谢械薪懈泄" },
      { "w": "eloquent", "p": "/藞el.蓹.kw蓹nt/", "t": "泻褉邪褋薪芯屑芯胁薪懈泄 / 锌械褉械泻芯薪谢懈胁懈泄" },
      { "w": "elusive", "p": "/i藞lu藧.s瑟v/", "t": "薪械胁谢芯胁懈屑懈泄 / 褟泻芯谐芯 胁邪卸泻芯 写芯褋褟谐褌懈" },
      { "w": "eminent", "p": "/藞em.瑟.nent/", "t": "胁懈写邪褌薪懈泄 / 蟹薪邪屑械薪懈褌懈泄" },
      { "w": "empirical", "p": "/em藞p瑟r.瑟.k蓹l/", "t": "械屑锌褨褉懈褔薪懈泄 / 蟹邪褋薪芯胁邪薪懈泄 薪邪 写芯褋胁褨写褨" },
      { "w": "encourage", "p": "/瑟n藞k蕦r.瑟d蕭/", "t": "蟹邪芯褏芯褔褍胁邪褌懈 / 锌褨写斜邪写褜芯褉褞胁邪褌懈" },
      { "w": "endeavor", "p": "/瑟n藞dev.蓹r/", "t": "蟹褍褋懈谢谢褟 / 锌褉邪谐薪械薪薪褟 / 褋锌褉芯斜邪" },
      { "w": "enhance", "p": "/瑟n藞h蓱藧ns/", "t": "锌芯泻褉邪褖褍胁邪褌懈 / 锌芯褋懈谢褞胁邪褌懈 / 锌褨写胁懈褖褍胁邪褌懈 褟泻褨褋褌褜" },
      { "w": "equivocal", "p": "/瑟藞kw瑟v.蓹.k蓹l/", "t": "写胁芯蟹薪邪褔薪懈泄 / 薪械胁懈蟹薪邪褔械薪懈泄" },
      { "w": "eradicate", "p": "/瑟藞r忙d.瑟.ke瑟t/", "t": "胁懈泻芯褉褨薪褞胁邪褌懈 / 蟹薪懈褖褍胁邪褌懈" },
      { "w": "erratic", "p": "/瑟藞r忙t.瑟k/", "t": "薪械锌械褉械写斜邪褔褍胁邪薪懈泄 / 屑褨薪谢懈胁懈泄 / 薪械锌芯褋褌褨泄薪懈泄" },
      { "w": "evade", "p": "/瑟藞ve瑟d/", "t": "褍薪懈泻邪褌懈 / 褍褏懈谢褟褌懈褋褟" },
      { "w": "evoke", "p": "/瑟藞v蓹蕣k/", "t": "胁懈泻谢懈泻邪褌懈 (褋锌芯谐邪写懈, 锌芯褔褍褌褌褟)" },
      { "w": "exaggerate", "p": "/瑟伞藞z忙d蕭.蓹.re瑟t/", "t": "锌械褉械斜褨谢褜褕褍胁邪褌懈" },
      { "w": "exemplify", "p": "/瑟伞藞zem.pl瑟.fa瑟/", "t": "褋谢褍卸懈褌懈 锌褉懈泻谢邪写芯屑 / 褨谢褞褋褌褉褍胁邪褌懈" },
      { "w": "explicit", "p": "/瑟k藞spl瑟s.瑟t/", "t": "褟胁薪懈泄 / 褌芯褔薪懈泄 / 胁褨写胁械褉褌懈泄" },
      { "w": "exploit", "p": "/瑟k藞spl蓴瑟t/", "t": "械泻褋锌谢褍邪褌褍胁邪褌懈 / 胁懈泻芯褉懈褋褌芯胁褍胁邪褌懈 褍 褋胁芯褩褏 褑褨谢褟褏" },
      { "w": "feasible", "p": "/藞fi藧.z蓹.b蓹l/", "t": "蟹写褨泄褋薪械薪薪懈泄 / 屑芯卸谢懈胁懈泄 / 褉械邪谢褜薪懈泄" },
      { "w": "frequent", "p": "/藞fri藧.kw蓹nt/", "t": "褔邪褋褌懈泄 / 锌芯胁褌芯褉褞胁邪薪懈泄" },
      { "w": "frivolous", "p": "/藞fr瑟v.蓹l.蓹s/", "t": "谢械谐泻芯胁邪卸薪懈泄 / 锌芯胁械褉褏芯胁懈泄 / 薪械褋械褉泄芯蟹薪懈泄" },
      { "w": "gauge", "p": "/伞e瑟d蕭/", "t": "芯褑褨薪褞胁邪褌懈 / 胁懈屑褨褉褞胁邪褌懈" },
      { "w": "genuine", "p": "/藞d蕭en.ju.瑟n/", "t": "褋锌褉邪胁卸薪褨泄 / 褖懈褉懈泄" },
      { "w": "grievance", "p": "/藞伞ri藧.v蓹ns/", "t": "褋泻邪褉谐邪 / 芯斜褉邪蟹邪 / 薪械胁写芯胁芯谢械薪薪褟" },
      { "w": "gullible", "p": "/藞伞蕦l.蓹.b蓹l/", "t": "写芯胁褨褉谢懈胁懈泄 / 薪邪褩胁薪懈泄" },
      { "w": "hinder", "p": "/藞h瑟n.d蓹r/", "t": "锌械褉械褕泻芯写卸邪褌懈 / 蟹邪胁邪卸邪褌懈" },
      { "w": "hostile", "p": "/藞h蓲s.ta瑟l/", "t": "胁芯褉芯卸懈泄 / 薪械写褉褍卸薪褨泄" },
      { "w": "hypocrisy", "p": "/h瑟藞p蓲k.r蓹.si/", "t": "谢懈褑械屑褨褉褋褌胁芯 / 褏邪薪卸械褋褌胁芯" },
      { "w": "illuminate", "p": "/瑟藞lu藧.m瑟.ne瑟t/", "t": "芯褋胁褨褌谢褞胁邪褌懈 / 褉芯蟹'褟褋薪褞胁邪褌懈" },
      { "w": "imagine", "p": "/瑟藞m忙d蕭.瑟n/", "t": "褍褟胁谢褟褌懈" },
      { "w": "imminent", "p": "/藞瑟m.瑟.n蓹nt/", "t": "薪械屑懈薪褍褔懈泄 / 蟹邪谐褉芯蟹谢懈胁懈泄 (锌褉芯 薪械斜械蟹锌械泻褍)" },
      { "w": "imply", "p": "/瑟m藞pla瑟/", "t": "屑邪褌懈 薪邪 褍胁邪蟹褨 / 薪邪褌褟泻邪褌懈" },
      { "w": "impoverished", "p": "/瑟m藞p蓲v.蓹r.瑟蕛t/", "t": "蟹斜褨写薪褨谢懈泄 / 胁懈褋薪邪卸械薪懈泄" },
      { "w": "incentive", "p": "/瑟n藞sen.t瑟v/", "t": "褋褌懈屑褍谢 / 褋锌芯薪褍泻邪薪薪褟 / 屑芯褌懈胁" },
      { "w": "indifferent", "p": "/瑟n藞d瑟f.蓹r.蓹nt/", "t": "斜邪泄写褍卸懈泄 / 薪械蟹邪褑褨泻邪胁谢械薪懈泄" },
      { "w": "indigenous", "p": "/瑟n藞d瑟d蕭.瑟.n蓹s/", "t": "泻芯褉褨薪薪懈泄 / 屑褨褋褑械胁懈泄" },
      { "w": "inevitable", "p": "/瑟n藞ev.瑟.t蓹.b蓹l/", "t": "薪械屑懈薪褍褔懈泄 / 薪械胁褨写胁芯褉芯褌薪懈泄" },
      { "w": "infer", "p": "/瑟n藞f蓽藧r/", "t": "褉芯斜懈褌懈 胁懈褋薪芯胁芯泻 / 锌褉懈锌褍褋泻邪褌懈" },
      { "w": "ingenious", "p": "/瑟n藞d蕭i藧.ni.蓹s/", "t": "胁懈薪邪褏褨写谢懈胁懈泄 / 屑邪泄褋褌械褉薪懈泄 / 谐械薪褨邪谢褜薪懈泄" },
      { "w": "inherent", "p": "/瑟n藞h瑟蓹.r蓹nt/", "t": "胁褉芯写卸械薪懈泄 / 薪械胁褨写'褦屑薪懈泄" },
      { "w": "innovative", "p": "/藞瑟n.蓹.v蓹.t瑟v/", "t": "褨薪薪芯胁邪褑褨泄薪懈泄 / 薪芯胁邪褌芯褉褋褜泻懈泄" },
      { "w": "insatiable", "p": "/瑟n藞se瑟.蕛蓹.b蓹l/", "t": "薪械薪邪褋懈褌薪懈泄 / 卸邪写褨斜薪懈泄" },
      { "w": "integrate", "p": "/藞瑟n.t瑟.伞re瑟t/", "t": "褨薪褌械谐褉褍胁邪褌懈 / 芯斜'褦写薪褍胁邪褌懈" },
      { "w": "intricate", "p": "/藞瑟n.tr瑟.k蓹t/", "t": "蟹邪锌谢褍褌邪薪懈泄 / 褋泻谢邪写薪懈泄" },
      { "w": "invaluable", "p": "/瑟n藞v忙l.ju.蓹.b蓹l/", "t": "斜械蟹褑褨薪薪懈泄" },
      { "w": "judicious", "p": "/d蕭u藧藞d瑟蕛.蓹s/", "t": "褉芯蟹胁邪卸谢懈胁懈泄 / 褉芯蟹褋褍写谢懈胁懈泄" },
      { "w": "manage", "p": "/藞m忙n.瑟d蕭/", "t": "泻械褉褍胁邪褌懈 / 褋锌褉邪胁谢褟褌懈褋褟" },
      { "w": "reduce", "p": "/r瑟藞d蕭u藧s/", "t": "蟹屑械薪褕褍胁邪褌懈 / 蟹薪懈卸褍胁邪褌懈" }
    ],
    "C2": [
      { "w": "aberration", "p": "/藢忙b.蓹藞re瑟.蕛蓹n/", "t": "胁褨写褏懈谢械薪薪褟 胁褨写 薪芯褉屑懈 / 邪斜械褉邪褑褨褟" },
      { "w": "anachronism", "p": "/蓹藞n忙k.r蓹.n瑟z.蓹m/", "t": "邪薪邪褏褉芯薪褨蟹屑 / 蟹邪褋褌邪褉褨谢械 褟胁懈褖械" },
      { "w": "cacophony", "p": "/k蓹藞k蓲f.蓹.ni/", "t": "泻邪泻芯褎芯薪褨褟 / 写懈褋谐邪褉屑芯薪褨褟 蟹胁褍泻褨胁" },
      { "w": "epitome", "p": "/瑟藞p瑟t.蓹.mi/", "t": "胁褌褨谢械薪薪褟 / 褍芯褋芯斜谢械薪薪褟" },
      { "w": "idiosyncrasy", "p": "/藢瑟d.i.蓹藞s瑟艐.kr蓹.si/", "t": "褨写褨芯褋懈薪泻褉邪蟹褨褟 / 褨薪写懈胁褨写褍邪谢褜薪邪 芯褋芯斜谢懈胁褨褋褌褜" },
      { "w": "juxtaposition", "p": "/藢d蕭蕦k.st蓹.p蓹藞z瑟蕛.蓹n/", "t": "蟹褨褋褌邪胁谢械薪薪褟 / 薪邪泻谢邪写邪薪薪褟 褋屑懈褋谢褨胁" },
      { "w": "nefarious", "p": "/n蓹藞fe蓹.ri.蓹s/", "t": "屑械褉蟹械薪薪懈泄 / 锌褨写谢懈泄 / 薪械褔械褋褌懈胁懈泄" },
      { "w": "obfuscate", "p": "/藞蓲b.f蕦s.ke瑟t/", "t": "蟹邪锌谢褍褌褍胁邪褌懈 / 薪邪胁屑懈褋薪芯 褍褋泻谢邪写薪褞胁邪褌懈" },
      { "w": "quintessential", "p": "/藢kw瑟n.t瑟藞sen.蕛蓹l/", "t": "褌懈锌芯胁懈泄 / 褟泻懈泄 褦 薪邪泄泻褉邪褖懈屑 锌褉懈泻谢邪写芯屑" },
      { "w": "sycophant", "p": "/藞s瑟k.蓹.f忙nt/", "t": "锌褨写谢邪斜褍蟹薪懈泻 / 锌褨写谢械褋谢懈胁邪 谢褞写懈薪邪" },
      { "w": "acquiesce", "p": "/藢忙k.wi藞es/", "t": "屑芯胁褔邪蟹薪芯 锌芯谐芯写卸褍胁邪褌懈褋褟 / 锌芯褋褌褍锌邪褌懈褋褟" },
      { "w": "benevolent", "p": "/b蓹藞nev.蓹l.蓹nt/", "t": "写芯斜褉芯蟹懈褔谢懈胁懈泄 / 斜谢邪谐芯写褨泄薪懈泄" },
      { "w": "capricious", "p": "/k蓹藞pr瑟蕛.蓹s/", "t": "泻邪锌褉懈蟹薪懈泄 / 屑褨薪谢懈胁懈泄" },
      { "w": "deleterious", "p": "/藢del.瑟藞t瑟蓹.ri.蓹s/", "t": "褕泻褨写谢懈胁懈泄 / 蟹谐褍斜薪懈泄" },
      { "w": "ephemeral", "p": "/瑟藞fem.蓹r.蓹l/", "t": "械褎械屑械褉薪懈泄 / 褋泻芯褉芯屑懈薪褍褔懈泄" },
      { "w": "garrulous", "p": "/藞伞忙r.蓹l.蓹s/", "t": "斜邪谢邪泻褍褔懈泄 / 谐芯胁褨褉泻懈泄" },
      { "w": "inherent", "p": "/瑟n藞h瑟蓹.r蓹nt/", "t": "胁谢邪褋褌懈胁懈泄 / 胁褉芯写卸械薪懈泄 / 薪械胁褨写'褦屑薪懈泄" },
      { "w": "meticulous", "p": "/m蓹藞t瑟k.j蓹.l蓹褋/", "t": "褉械褌械谢褜薪懈泄 / 锌械写邪薪褌懈褔薪懈泄" },
      { "w": "pernicious", "p": "/p蓹藞n瑟蕛.蓹s/", "t": "蟹谐褍斜薪懈泄 / 褕泻褨写谢懈胁懈泄 / 薪械斜械蟹锌械褔薪懈泄" },
      { "w": "ubiquitous", "p": "/ju藧藞b瑟k.w瑟.t蓹s/", "t": "锌芯胁褋褞写薪懈泄 / 褟泻懈泄 褦 褋泻褉褨蟹褜" },
      { "w": "alacrity", "p": "/蓹藞l忙k.r蓹.ti/", "t": "谐芯褌芯胁薪褨褋褌褜 / 卸胁邪胁褨褋褌褜 / 蟹邪锌邪谢" },
      { "w": "anathema", "p": "/蓹藞n忙胃.蓹m.蓹/", "t": "邪薪邪褎械屑邪 / 锌褉芯泻谢褟褌褌褟 / 芯谐懈写薪械 褟胁懈褖械" },
      { "w": "assiduous", "p": "/蓹藞s瑟d.ju.蓹s/", "t": "褋褌邪褉邪薪薪懈泄 / 薪邪锌芯谢械谐谢懈胁懈泄" },
      { "w": "audacious", "p": "/蓴藧藞de瑟.蕛蓹s/", "t": "蟹褍褏胁邪谢懈泄 / 褋屑褨谢懈胁懈泄 / 胁褨写褔邪泄写褍褕薪懈泄" },
      { "w": "clandestine", "p": "/kl忙n藞des.t瑟n/", "t": "褌邪褦屑薪懈泄 / 锌褨写锌褨谢褜薪懈泄 / 锌褉懈褏芯胁邪薪懈泄" },
      { "w": "conundrum", "p": "/k蓹藞n蕦n.dr蓹m/", "t": "谐芯谢芯胁芯谢芯屑泻邪 / 蟹邪锌谢褍褌邪薪邪 蟹邪谐邪写泻邪" },
      { "w": "dearth", "p": "/d蓽藧胃/", "t": "薪械褋褌邪褔邪 / 写械褎褨褑懈褌" },
      { "w": "dogmatic", "p": "/d蓲伞藞m忙t.瑟k/", "t": "写芯谐屑邪褌懈褔薪懈泄 / 泻邪褌械谐芯褉懈褔薪懈泄" },
      { "w": "eclectic", "p": "/ek藞lek.t瑟k/", "t": "械泻谢械泻褌懈褔薪懈泄 / 褉褨蟹薪芯斜褨褔薪懈泄" },
      { "w": "gregarious", "p": "/伞r瑟藞伞e蓹.ri.蓹s/", "t": "褌芯胁邪褉懈褋褜泻懈泄 / 褋褌邪写薪懈泄" },
      { "w": "harangue", "p": "/h蓹藞r忙艐/", "t": "锌邪谢泻邪 锌褉芯屑芯胁邪 / 锌邪谢泻懈泄 胁懈褋褌褍锌" },
      { "w": "impetuous", "p": "/瑟m藞pet蕛.u.蓹s/", "t": "褨屑锌褍谢褜褋懈胁薪懈泄 / 薪械褋褌褉懈屑薪懈泄" },
      { "w": "insidious", "p": "/瑟n藞s瑟d.i.蓹s/", "t": "锌褨写褋褌褍锌薪懈泄 / 褏懈褌褉懈泄" },
      { "w": "lucid", "p": "/藞lu藧.s瑟d/", "t": "褟褋薪懈泄 / 蟹褉芯蟹褍屑褨谢懈泄 / 锌褉芯蟹芯褉懈泄" },
      { "w": "maverick", "p": "/藞m忙v.蓹r.瑟k/", "t": "褨薪邪泻芯写褍屑械褑褜 / 薪械蟹邪谢械卸薪邪 谢褞写懈薪邪" },
      { "w": "obdurate", "p": "/藞蓲b.d蕭蓹.r蓹t/", "t": "胁锌械褉褌懈泄 / 薪械锌芯褏懈褌薪懈泄 / 褔械褉褋褌胁懈泄" },
      { "w": "ostentatious", "p": "/藢蓲s.ten藞te瑟.蕛蓹s/", "t": "薪邪胁屑懈褋薪懈泄 / 锌懈褏邪褌懈泄 / 写械屑芯薪褋褌褉邪褌懈胁薪懈泄" },
      { "w": "paragon", "p": "/藞p忙r.蓹.伞蓹n/", "t": "蟹褉邪蟹芯泻 / 械褌邪谢芯薪 / 褨写械邪谢" },
      { "w": "plethora", "p": "/藞ple胃.蓹r.蓹/", "t": "薪邪写谢懈褕芯泻 / 斜械蟹谢褨褔" },
      { "w": "pragmatic", "p": "/pr忙伞藞m忙t.瑟k/", "t": "锌褉邪谐屑邪褌懈褔薪懈泄 / 褉械邪谢褨褋褌懈褔薪懈泄" },
      { "w": "recalcitrant", "p": "/r瑟藞k忙l.s瑟.tr蓹nt/", "t": "薪械锌芯泻褨褉薪懈泄 / 胁锌械褉褌懈泄" },
      { "w": "sanctimonious", "p": "/藢s忙艐k.t瑟藞m蓹蕣.ni.蓹s/", "t": "褏邪薪卸械褋褜泻懈泄 / 褋胁褟褌械薪薪懈褑褜泻懈泄" },
      { "w": "truculent", "p": "/藞tr蕦k.j蓹.l蓹nt/", "t": "邪谐褉械褋懈胁薪懈泄 / 谐褉褍斜懈泄 / 胁芯泄芯胁薪懈褔懈泄" },
      { "w": "vacillate", "p": "/藞v忙s.瑟.le瑟t/", "t": "胁邪谐邪褌懈褋褟 / 锌褉芯褟胁谢褟褌懈 薪械褉褨褕褍褔褨褋褌褜" },
      { "w": "venerable", "p": "/藞ven.蓹r.蓹.b蓹l/", "t": "褕邪薪芯胁邪薪懈泄 / 锌芯胁邪卸薪懈泄" },
      { "w": "vociferous", "p": "/v蓹藞s瑟f.蓹r.蓹s/", "t": "谐邪谢邪褋谢懈胁懈泄 / 谐褍褔薪懈泄" },
      { "w": "zenith", "p": "/藞zen.瑟胃/", "t": "蟹械薪褨褌 / 胁械褉褕懈薪邪 / 泻褍谢褜屑褨薪邪褑褨褟" },
      { "w": "acquittal", "p": "/蓹藞kw瑟t.蓹l/", "t": "胁懈锌褉邪胁写邪薪薪褟 / 胁懈锌褉邪胁写褍胁邪谢褜薪懈泄 胁懈褉芯泻" },
      { "w": "adulation", "p": "/藢忙d.j蓹藞le瑟.蕛蓹n/", "t": "谢械褋褌芯褖褨 / 薪邪写屑褨褉薪械 蟹邪褏芯锌谢械薪薪褟" },
      { "w": "aesthetic", "p": "/es藞胃et.瑟k/", "t": "械褋褌械褌懈褔薪懈泄" },
      { "w": "amicable", "p": "/藞忙m.瑟.k蓹.b蓹l/", "t": "写褉褍卸薪褨泄 / 写芯斜褉芯蟹懈褔谢懈胁懈泄" },
      { "w": "antithesis", "p": "/忙n藞t瑟胃.蓹.s瑟s/", "t": "邪薪褌懈褌械蟹邪 / 锌芯胁薪邪 锌褉芯褌懈谢械卸薪褨褋褌褜" },
      { "w": "austere", "p": "/蓲st藞瑟蓹r/", "t": "褋褍胁芯褉懈泄 / 邪褋泻械褌懈褔薪懈泄" },
      { "w": "belligerent", "p": "/b蓹藞l瑟d蕭.蓹r.蓹nt/", "t": "胁芯泄芯胁薪懈褔懈泄 / 邪谐褉械褋懈胁薪懈泄" },
      { "w": "candor", "p": "/藞k忙n.d蓹r/", "t": "胁褨写胁械褉褌褨褋褌褜 / 褖懈褉褨褋褌褜" },
      { "w": "chicanery", "p": "/蕛瑟藞ke瑟.n蓹r.i/", "t": "泻褉褍褌褨泄褋褌胁芯 / 屑邪褏褨薪邪褑褨褩 / 褋芯褎褨褋褌懈泻邪" },
      { "w": "cogent", "p": "/藞k蓹蕣.d蕭蓹nt/", "t": "锌械褉械泻芯薪谢懈胁懈泄 / 芯斜覒褉褍薪褌芯胁邪薪懈泄" },
      { "w": "compunction", "p": "/k蓹m藞p蕦艐k.蕛蓹n/", "t": "写芯泻芯褉懈 褋褍屑谢褨薪薪褟 / 泻邪褟褌褌褟" },
      { "w": "decorum", "p": "/d瑟藞k蓴藧.r蓹m/", "t": "锌褉懈褋褌芯泄薪褨褋褌褜 / 械褌懈泻械褌" },
      { "w": "deference", "p": "/藞def.蓹r.蓹ns/", "t": "锌芯胁邪谐邪 / 褕邪薪邪 / 锌褨写泻芯褉械薪薪褟" },
      { "w": "despot", "p": "/藞des.p蓲t/", "t": "写械褋锌芯褌 / 褌懈褉邪薪" },
      { "w": "didactic", "p": "/da瑟藞d忙k.t瑟k/", "t": "锌芯胁褔邪谢褜薪懈泄 / 写懈写邪泻褌懈褔薪懈泄" },
      { "w": "disparate", "p": "/藞d瑟s.p蓹r.蓹t/", "t": "薪械锌芯褉褨胁薪褟薪薪懈泄 / 褉褨蟹薪芯褉褨写薪懈泄" },
      { "w": "duplicity", "p": "/d蕭u藧藞pl瑟s.蓹.ti/", "t": "写胁芯褉褍褕薪懈褑褌胁芯 / 芯斜屑邪薪" },
      { "w": "effrontery", "p": "/瑟藞fr蕦n.t蓹r.i/", "t": "薪邪褏邪斜褋褌胁芯 / 蟹褍褏胁邪谢褨褋褌褜" },
      { "w": "egregious", "p": "/瑟藞伞ri藧.d蕭蓹s/", "t": "泻褉懈褔褍褖懈泄 / 卸邪褏谢懈胁懈泄" },
      { "w": "eloquent", "p": "/藞el.蓹.kw蓹nt/", "t": "泻褉邪褋薪芯屑芯胁薪懈泄" },
      { "w": "enervate", "p": "/藞en.蓹.ve瑟t/", "t": "蟹薪械褋懈谢褞胁邪褌懈 / 芯褋谢邪斜谢褞胁邪褌懈" },
      { "w": "enigma", "p": "/蓹藞n瑟伞.m蓹/", "t": "蟹邪谐邪写泻邪 / 褌邪褦屑薪懈褑褟" },
      { "w": "exculpate", "p": "/藞ek.sk蕦l.pe瑟t/", "t": "胁懈锌褉邪胁写芯胁褍胁邪褌懈 / 蟹薪褨屑邪褌懈 锌褉芯胁懈薪褍" },
      { "w": "facetious", "p": "/f蓹藞si藧.蕛蓹s/", "t": "卸邪褉褌褨胁谢懈胁懈泄 / 写芯褌械锌薪懈泄 (薪械写芯褉械褔薪芯)" },
      { "w": "fastidious", "p": "/f忙s藞t瑟d.i.蓹s/", "t": "胁懈斜邪谐谢懈胁懈泄 / 斜褉械蟹谐谢懈胁懈泄" },
      { "w": "frenetic", "p": "/fr蓹藞net.瑟k/", "t": "褋泻邪卸械薪懈泄 / 谐邪褉褟褔泻芯胁懈泄 / 褕邪谢械薪懈泄" },
      { "w": "furtive", "p": "/藞f蓽藧.t瑟v/", "t": "褌邪褦屑薪懈泄 / 泻褉邪写谢懈胁懈泄" },
      { "w": "grandiose", "p": "/藞伞r忙n.di.蓹蕣s/", "t": "谐褉邪薪写褨芯蟹薪懈泄 / 锌芯屑锌械蟹薪懈泄" },
      { "w": "gratuitous", "p": "/伞r蓹藞t蕛u藧.瑟.t蓹s/", "t": "斜械蟹锌褨写褋褌邪胁薪懈泄 / 斜械蟹泻芯褕褌芯胁薪懈泄" },
      { "w": "hapless", "p": "/藞h忙p.l蓹s/", "t": "薪械褖邪褋薪懈泄 / 斜械蟹褌邪谢邪薪薪懈泄" },
      { "w": "hegemony", "p": "/h瑟藞伞em.蓹.ni/", "t": "谐械谐械屑芯薪褨褟 / 锌邪薪褍胁邪薪薪褟" },
      { "w": "impeccable", "p": "/瑟m藞pek.蓹.b蓹l/", "t": "斜械蟹写芯谐邪薪薪懈泄 / 薪械锌芯谐褉褨褕薪懈泄" },
      { "w": "impudent", "p": "/藞瑟m.pj蓹.d蓹nt/", "t": "蟹褍褏胁邪谢懈泄 / 斜械蟹褋芯褉芯屑薪懈泄" },
      { "w": "incisive", "p": "/瑟n藞sa瑟.s瑟v/", "t": "谐芯褋褌褉褨泄 / 锌褉芯薪懈泻谢懈胁懈泄 / 褍褩写谢懈胁懈泄" },
      { "w": "indolent", "p": "/藞瑟n.d蓹l.蓹nt/", "t": "谢褨薪懈胁懈泄 / 屑谢褟胁懈泄" },
      { "w": "intrepid", "p": "/瑟n藞trep.瑟d/", "t": "斜械蟹褋褌褉邪褕薪懈泄 / 胁褨写胁邪卸薪懈泄" },
      { "w": "inundate", "p": "/藞瑟n.蕦n.de瑟t/", "t": "蟹邪褌芯锌谢褞胁邪褌懈 / 蟹邪褋懈锌邪褌懈 (蟹邪锌懈褌邪屑懈)" },
      { "w": "laconic", "p": "/l蓹藞k蓲n.瑟k/", "t": "谢邪泻芯薪褨褔薪懈泄 / 泻芯褉芯褌泻懈泄" },
      { "w": "largesse", "p": "/l蓱藧藞d蕭es/", "t": "褖械写褉褨褋褌褜 / 褖械写褉褨 写邪褉懈" },
      { "w": "latent", "p": "/藞le瑟.t蓹nt/", "t": "锌褉懈褏芯胁邪薪懈泄 / 谢邪褌械薪褌薪懈泄" },
      { "w": "malleable", "p": "/藞m忙l.i.蓹.b蓹l/", "t": "锌褨写写邪褌谢懈胁懈泄 / 谐薪褍褔泻懈泄" },
      { "w": "modicum", "p": "/藞m蓲d.瑟.k蓹m/", "t": "泻褉懈褏褌邪 / 薪械胁械谢懈泻邪 泻褨谢褜泻褨褋褌褜" },
      { "w": "myriad", "p": "/藞m瑟r.i.蓹d/", "t": "薪械蟹谢褨褔械薪薪邪 泻褨谢褜泻褨褋褌褜" },
      { "w": "nadir", "p": "/藞ne瑟.d瑟蓹r/", "t": "薪邪泄薪懈卸褔邪 褌芯褔泻邪 / 蟹邪薪械锌邪写" },
      { "w": "novice", "p": "/藞n蓲v.瑟s/", "t": "薪芯胁邪褔芯泻 / 锌芯褔邪褌泻褨胁械褑褜" },
      { "w": "nuance", "p": "/藞nju藧.蓱藧ns/", "t": "薪褞邪薪褋 / 胁褨写褌褨薪芯泻" },
      { "w": "obsequious", "p": "/蓹b藞si藧.kwi.蓹s/", "t": "写芯谐褨写谢懈胁懈泄 / 锌褨写谢械褋谢懈胁懈泄" },
      { "w": "panacea", "p": "/藢p忙n.蓹藞si藧.蓹/", "t": "锌邪薪邪褑械褟 / 褍薪褨胁械褉褋邪谢褜薪褨 谢褨泻懈" },
      { "w": "paucity", "p": "/藞p蓴藧.s蓹.ti/", "t": "薪械褋褌邪褔邪 / 斜褨写薪褨褋褌褜 / 屑邪谢褨褋褌褜" },
      { "w": "penchant", "p": "/藞p蓲n.蕛蓲n/", "t": "褋褏懈谢褜薪褨褋褌褜 / 褌褟谐邪 / 锌褉懈褋褌褉邪褋褌褜" },
      { "w": "perfunctory", "p": "/p蓹藞f蕦艐k.t蓹r.i/", "t": "锌芯胁械褉褏薪械胁懈泄 / 薪械写斜邪谢懈泄 / 褎芯褉屑邪谢褜薪懈泄" },
      { "w": "pithy", "p": "/藞p瑟胃.i/", "t": "蟹屑褨褋褌芯胁薪懈泄 / 褋褌懈褋谢懈泄 褌邪 胁谢褍褔薪懈泄" },
      { "w": "scrupulous", "p": "/藞skru藧.pj蓹.l蓹s/", "t": "褋褍屑谢褨薪薪懈泄 / 褔械褋薪懈泄 / 褉械褌械谢褜薪懈泄" }
    ]
  },
  "german": {
    "A1": [
      { "w": "Apfel", "p": "[藞apf蓹l]", "t": "褟斜谢褍泻芯" },
      { "w": "Buch", "p": "[bu藧x]", "t": "泻薪懈谐邪" }
    ],
    "A2": [],
    "B1": [],
    "B2": [],
    "C1": [],
    "C2": []
  }
}
